client/__init__.py
client/__main__.py
client/input.py
epicman/__init__.py
epicman/common.py
epicman/constants.py
epicman/logging.py
epicman/objects.py
epicman/py.typed
epicman/syscalls.py
epicman/version.py
epicman/client/__init__.py
epicman/client/__main__.py
epicman/client/input.py
epicman/game/__init__.py
epicman/game/socket.py
epicman/game/utils.py
epicman/helpers/__init__.py
epicman/helpers/file.py
epicman/helpers/socket.py
epicman/helpers/utils.py
epicman/middleware/__init__.py
epicman/middleware/mesh.py
epicman/middleware/performance.py
epicman/middleware/protocol.py
epicman/middleware/dns/__init__.py
epicman/middleware/dns/dnspython.py
epicman/middleware/dns/mdns.py
epicman/middleware/homa/__init__.py
epicman/protocol/__init__.py
epicman/server/__init__.py
epicman/server/__main__.py
epicman/server/gc.py
epicman/server/mesh.py
epicman/server/startup.py
epicman/server/syscalls.py
epicman/server/utils.py
epicman/server/db/__init__.py
epicman/server/db/dbm.py
epicman/server/db/dict.py
epicman/server/db/lmdb.py
epicman/server/db/sqlite.py
epicman/server/db/utils.py
epicman/server/dns/__init__.py
epicman/server/dns/dnspython.py
epicman/server/dns/mdns.py
epicman/server/helpers/__init__.py
epicman/server/helpers/file.py
epicserver-0.2.8.dist-info/LICENSE
epicserver-0.2.8.dist-info/METADATA
epicserver-0.2.8.dist-info/WHEEL
epicserver-0.2.8.dist-info/entry_points.txt
epicserver-0.2.8.dist-info/top_level.txt
epicserver-0.2.8.dist-info/zip-safe
epicserver-0.2.8.dist-info/RECORD
